{"name": "D - Equal Cut", "group": "AtCoder - AtCoder Beginner Contest 102", "url": "https://atcoder.jp/contests/abc102/tasks/arc100_b", "interactive": false, "memoryLimit": 1024, "timeLimit": 2000, "tests": [{"input": "5\n3 2 4 1 2\n", "output": "2\n"}, {"input": "10\n10 71 84 33 6 47 23 25 52 64\n", "output": "36\n"}, {"input": "7\n1 2 3 1000000000 4 5 6\n", "output": "999999994\n"}], "testType": "single", "input": {"type": "stdin"}, "output": {"type": "stdout"}, "languages": {"java": {"mainClass": "Main", "taskClass": "DEqualCut"}}}